[
  {
    "id": "earthhero-online",
    "name": "EarthHero",
    "description": "Online marketplace for sustainable products across all categories. Curated selection of eco-friendly brands with carbon-neutral shipping and plastic-free packaging.",
    "categories": ["sustainable-goods", "online-only"],
    "type": "online",
    "website": "https://earthhero.com",
    "contact": {
      "email": "support@earthhero.com"
    },
    "location": {
      "city": "Boulder",
      "state": "CO",
      "country": "USA"
    },
    "social": {
      "instagram": "@earthhero",
      "facebook": "earthhero",
      "twitter": "@earthhero"
    },
    "addedDate": "2024-01-20",
    "lastVerified": "2024-01-20",
    "status": "active"
  },
  {
    "id": "package-free-shop-online",
    "name": "Package Free Shop",
    "description": "Founded by zero-waste advocate Lauren Singer. Online store offering plastic-free alternatives for everyday products, from kitchen to bathroom to on-the-go.",
    "categories": ["zero-waste", "sustainable-goods", "online-only"],
    "type": "online",
    "website": "https://packagefreeshop.com",
    "contact": {
      "email": "hello@packagefreeshop.com"
    },
    "location": {
      "city": "Brooklyn",
      "state": "NY",
      "country": "USA"
    },
    "social": {
      "instagram": "@packagefreeshop",
      "facebook": "packagefreeshop"
    },
    "addedDate": "2024-01-20",
    "lastVerified": "2024-01-20",
    "status": "active"
  }
]
